StrongPasswordGenerator/__init__.py
StrongPasswordGenerator/cli.py
StrongPasswordGenerator/main.py
StrongPasswordGenerator-0.1.2.dist-info/METADATA
StrongPasswordGenerator-0.1.2.dist-info/WHEEL
StrongPasswordGenerator-0.1.2.dist-info/entry_points.txt
StrongPasswordGenerator-0.1.2.dist-info/top_level.txt
StrongPasswordGenerator-0.1.2.dist-info/RECORD
