Metadata-Version: 2.1
Name: StrongPasswordGenerator
Version: 0.1.2
Summary: Generates a strong password
Home-page: http://github.com/ogelami/StrongPasswordGenerator
Author: ogelami
Author-email: ogelami@gmail.com
License: MIT
